twitter2discord/__init__.py
twitter2discord/discord_hooks.py
twitter2discord/twitter2discord.py
twitter2discord/twitter_stream_listener.py
twitter2discord/utils.py
twitter2discord-0.1.6.dist-info/LICENSE
twitter2discord-0.1.6.dist-info/METADATA
twitter2discord-0.1.6.dist-info/WHEEL
twitter2discord-0.1.6.dist-info/top_level.txt
twitter2discord-0.1.6.dist-info/RECORD
