Metadata-Version: 2.1
Name: twitter2discord
Version: 0.1.6
Summary: Twitter to Discord Webhook
Home-page: https://github.com/poipoii/twitter2discord
Author: poipoii
Author-email: earth.sama@gmail.com
License: MIT
Keywords: twitter discord webhook
Platform: UNKNOWN
Classifier: Development Status :: 5 - Production/Stable
Classifier: License :: OSI Approved :: MIT License
Classifier: Programming Language :: Python
Classifier: Programming Language :: Python :: 3.4
Classifier: Programming Language :: Python :: 3.5
Classifier: Programming Language :: Python :: 3.6
Classifier: Topic :: Software Development :: Libraries
Requires-Dist: emoji (==0.5.1)
Requires-Dist: googletrans (==4.0.0-rc1)
Requires-Dist: requests (==2.20.0)
Requires-Dist: tweepy (==3.7.0)
